[
 {
  "title": "lxwqzejiwlfr",
  "description": "teuoaabor",
  "brand": "bvtlvszmnzmi",
  "model": "fwgnwkwvafr",
  "reference": "larqaoclizfr",
  "serial": "kohewzrecygb",
  "movement_no": "bzdzrtzfr",
  "movement": "cddittmgnmi",
  "timing": "fjkiosinoor",
  "waterproof": "bdaerdwypynwmi",
  "condition": "vwuufcsvyxr",
  "price": 10594943631440400,
  "sku": "fonsfehippvi",
  "deleted": true,
  "owners": [
   null,
   null,
   null,
   null,
   null,
   null,
   null,
   null,
   null,
   null
  ],
  "images": [
   {},
   {},
   {},
   {},
   {},
   {},
   {},
   {},
   {},
   {},
   {}
  ]
 },
 {
  "title": "qwuteuvoyqfr",
  "description": "mqovpldi",
  "brand": "oaqtgqyjnstt",
  "model": "xjgwmizqyr",
  "reference": "djpssukfbt",
  "serial": "gguidzcokor",
  "movement_no": "kqfelibxr",
  "movement": "phhnvafyjuxr",
  "timing": "ghlzwqwpzk",
  "waterproof": "pedkcfttsxlxr",
  "condition": "yshlxqtt",
  "price": 8796891723759472,
  "sku": "ykxpncfalnmi",
  "deleted": false,
  "owners": [
   null,
   null,
   null,
   null,
   null,
   null,
   null,
   null,
   null,
   null
  ],
  "images": [
   {},
   {},
   {},
   {},
   {},
   {},
   {},
   {},
   {},
   {},
   {}
  ]
 },
 {
  "title": "erxrhatoeeidxr",
  "description": "fvrmksqjbe",
  "brand": "itcfavgawbhgpr",
  "model": "zoyktncghkt",
  "reference": "fmaichbe",
  "serial": "ryxabtricnmi",
  "movement_no": "qchbcaelvkotji",
  "movement": "hgpyqvcdi",
  "timing": "qutmqdemzdi",
  "waterproof": "fdjfibubpkludi",
  "condition": "khxbtxdsi",
  "price": 10353885823860764,
  "sku": "tehgiivdnjcdi",
  "deleted": true,
  "owners": [
   null,
   null,
   null,
   null,
   null,
   null,
   null,
   null,
   null,
   null
  ],
  "images": [
   {},
   {},
   {},
   {},
   {},
   {},
   {},
   {},
   {},
   {},
   {}
  ]
 },
 {
  "title": "mmhliwubfor",
  "description": "ffwoqisybqfr",
  "brand": "veulairjngqcxr",
  "model": "xylplvozuxr",
  "reference": "jzoebsuxflxr",
  "serial": "hdwipkzfr",
  "movement_no": "hdxdbejgaatt",
  "movement": "ajaiqvvaemi",
  "timing": "izqbzkjaqsor",
  "waterproof": "aehjkgjmt",
  "condition": "jfxttrqczbyb",
  "price": 59957789024338130,
  "sku": "ymkbowwb",
  "deleted": false,
  "owners": [
   null,
   null,
   null,
   null,
   null,
   null,
   null,
   null,
   null,
   null
  ],
  "images": [
   {},
   {},
   {},
   {},
   {},
   {},
   {},
   {},
   {},
   {},
   {}
  ]
 },
 {
  "title": "yncobpxtfbt",
  "description": "ewqlujzoadafr",
  "brand": "vnuekkxxeisrk",
  "model": "qwakzvn",
  "reference": "dqballfdzkgvi",
  "serial": "ikizpwjcbdtpgb",
  "movement_no": "muxruqmi",
  "movement": "rwwzvasebxr",
  "timing": "nqarowhgb",
  "waterproof": "wmysejgurnqaor",
  "condition": "vkrumuhquxr",
  "price": 43725808756425976,
  "sku": "ckhqmdrmlxr",
  "deleted": false,
  "owners": [
   null,
   null,
   null,
   null,
   null,
   null,
   null,
   null,
   null,
   null
  ],
  "images": [
   {},
   {},
   {},
   {},
   {},
   {},
   {},
   {},
   {},
   {},
   {}
  ]
 },
 {
  "title": "igoxsdxai",
  "description": "sncebrosx",
  "brand": "ubvakmdyrpb",
  "model": "lxagcfpixk",
  "reference": "iwmtttnzeivai",
  "serial": "jnhthphjecdi",
  "movement_no": "igtzrqdjkfswcdi",
  "movement": "adbmuwizewmi",
  "timing": "wksoidzdvi",
  "waterproof": "eglsxmxepe",
  "condition": "tuqfvilwcdi",
  "price": 9599564026575536,
  "sku": "invbrmpanqiai",
  "deleted": false,
  "owners": [
   null,
   null,
   null,
   null,
   null,
   null,
   null,
   null,
   null,
   null
  ],
  "images": [
   {},
   {},
   {},
   {},
   {},
   {},
   {},
   {},
   {},
   {},
   {}
  ]
 },
 {
  "title": "lhyeupcqqzdvi",
  "description": "mrseaprwmi",
  "brand": "ukbrifbrwlfr",
  "model": "tjlaealoeizfr",
  "reference": "ytvsbtzxcjtt",
  "serial": "gppbfpjji",
  "movement_no": "qjqsrek",
  "movement": "ukgmsi",
  "timing": "lzorcsybdzehfr",
  "waterproof": "htghioknkt",
  "condition": "sygldktvsi",
  "price": 5840614235494286,
  "sku": "okqqhsfxbgvi",
  "deleted": false,
  "owners": [
   null,
   null,
   null,
   null,
   null,
   null,
   null,
   null,
   null,
   null
  ],
  "images": [
   {},
   {},
   {},
   {},
   {},
   {},
   {},
   {},
   {},
   {},
   {}
  ]
 },
 {
  "title": "brsrmqtoi",
  "description": "fgkehvovegcik",
  "brand": "wwiqfhw",
  "model": "fsxnkfrlcvvi",
  "reference": "jwpfjtakolxr",
  "serial": "smcscktor",
  "movement_no": "khbmogvcslusor",
  "movement": "fqfoheabgldi",
  "timing": "paixfcracik",
  "waterproof": "jadpwvwvcxr",
  "condition": "zqpdvlzcnxw",
  "price": 21002831496298310,
  "sku": "hnhrzywsi",
  "deleted": true,
  "owners": [
   null,
   null,
   null,
   null,
   null,
   null,
   null,
   null,
   null,
   null
  ],
  "images": [
   {},
   {},
   {},
   {},
   {},
   {},
   {},
   {},
   {},
   {},
   {}
  ]
 },
 {
  "title": "qasluik",
  "description": "imifzvdrnewmi",
  "brand": "waoypevokor",
  "model": "sdnbczjsxxbt",
  "reference": "ulzwurdwmlxr",
  "serial": "qknluirdgtak",
  "movement_no": "wmiollksyvi",
  "movement": "hyqmifhfflxr",
  "timing": "domyhsxajor",
  "waterproof": "tnaazkrtqpvi",
  "condition": "hcvsjljlpb",
  "price": 795497351558879,
  "sku": "yhrwqwyldi",
  "deleted": true,
  "owners": [
   null,
   null,
   null,
   null,
   null,
   null,
   null,
   null,
   null,
   null
  ],
  "images": [
   {},
   {},
   {},
   {},
   {},
   {},
   {},
   {},
   {},
   {},
   {}
  ]
 },
 {
  "title": "vtahybgoqolxr",
  "description": "ashqiavmxsthuxr",
  "brand": "lxjtgvmyujtt",
  "model": "naqjilfsmqdunmi",
  "reference": "igspllwqoxbt",
  "serial": "ewjrznpqifr",
  "movement_no": "rugufruiusyvi",
  "movement": "zdvwodvnmdlik",
  "timing": "egljzpqilik",
  "waterproof": "iajbxlosmvi",
  "condition": "cfcttfulvunmi",
  "price": 3296153654810041,
  "sku": "ubcjkyqilik",
  "deleted": true,
  "owners": [
   null,
   null,
   null,
   null,
   null,
   null,
   null,
   null,
   null,
   null
  ],
  "images": [
   {},
   {},
   {},
   {},
   {},
   {},
   {},
   {},
   {},
   {},
   {}
  ]
 },
 {
  "title": "prxoitvuzk",
  "description": "omxxgxnorpi",
  "brand": "dlzofecdi",
  "model": "zumesawnrk",
  "reference": "exvrpyabxr",
  "serial": "mnmdppqtzkt",
  "movement_no": "baanzckkwyfzuxr",
  "movement": "ybfmvdqjjor",
  "timing": "eqhedxdofr",
  "waterproof": "zwfdrldi",
  "condition": "cwkkbskzkt",
  "price": 612942102830857,
  "sku": "cgvvexadsaor",
  "deleted": false,
  "owners": [
   null,
   null,
   null,
   null,
   null,
   null,
   null,
   null,
   null,
   null
  ],
  "images": [
   {},
   {},
   {},
   {},
   {},
   {},
   {},
   {},
   {},
   {},
   {}
  ]
 }
]